sensirion_gas_index_algorithm/__init__.py
sensirion_gas_index_algorithm/_sensirion_gas_index_algorithm_wrap.cp38-win_amd64.pyd
sensirion_gas_index_algorithm/gas_index_algorithm.py
sensirion_gas_index_algorithm/nox_algorithm.py
sensirion_gas_index_algorithm/sensirion_gas_index_algorithm_wrap.py
sensirion_gas_index_algorithm/version.py
sensirion_gas_index_algorithm/voc_algorithm.py
sensirion_gas_index_algorithm-3.2.2.dist-info/LICENSE
sensirion_gas_index_algorithm-3.2.2.dist-info/METADATA
sensirion_gas_index_algorithm-3.2.2.dist-info/WHEEL
sensirion_gas_index_algorithm-3.2.2.dist-info/top_level.txt
sensirion_gas_index_algorithm-3.2.2.dist-info/RECORD
