Metadata-Version: 2.1
Name: sensirion-gas-index-algorithm
Version: 3.2.2
Summary: Sensirions public algorithms to calculate VOC and NOx gas indices.
Home-page: https://developers.sensirion.com
Author: Sensirion
Author-email: info@sensirion.com
License: BSD
Keywords: sensirion,gas-index,voc,nox,algorithm
Platform: UNKNOWN
Classifier: Intended Audience :: Developers
Classifier: License :: OSI Approved :: BSD License
Classifier: Programming Language :: Python :: 3.6
Classifier: Programming Language :: Python :: 3.7
Classifier: Programming Language :: Python :: 3.8
Classifier: Programming Language :: Python :: 3.9
Classifier: Programming Language :: Python :: 3.10
Classifier: Topic :: Software Development :: Libraries :: Python Modules
Requires-Python: >=3.6,<4
Provides-Extra: docs
Requires-Dist: sphinx (~=2.2.1) ; extra == 'docs'
Requires-Dist: sphinx-rtd-theme (~=1.0.0) ; extra == 'docs'
Provides-Extra: test
Requires-Dist: flake8 (~=3.7.8) ; extra == 'test'
Requires-Dist: pytest (~=4.6.11) ; extra == 'test'
Requires-Dist: pytest-cov (~=2.12.1) ; extra == 'test'
